{
  "resourceType": "Bundle",
  "type": "document",
  "entry": [
    {
      "resource": {
        "resourceType": "Patient",
        "id": "patient-1",
        "name": [
          {
            "text": "[REDACTED]"
          }
        ],
        "gender": "female",
        "age": 57,
        "identifier": [
          {
            "system": "urn:oid:2.16.840.1.113883.4.1",
            "value": "[REDACTED]"
          }
        ]
      }
    },
    {
      "resource": {
        "resourceType": "Encounter",
        "id": "encounter-1",
        "status": "finished",
        "class": {
          "system": "http://terminology.hl7.org/CodeSystem/v3-ActCode",
          "code": "IMP",
          "display": "inpatient encounter"
        },
        "subject": {
          "reference": "Patient/patient-1"
        },
        "period": {
          "start": "[REDACTED]",
          "end": "[REDACTED]"
        }
      }
    },
    {
      "resource": {
        "resourceType": "Condition",
        "id": "condition-1",
        "clinicalStatus": {
          "coding": [
            {
              "system": "http://terminology.hl7.org/CodeSystem/condition-clinical",
              "code": "active"
            }
          ]
        },
        "verificationStatus": {
          "coding": [
            {
              "system": "http://terminology.hl7.org/CodeSystem/condition-ver-status",
              "code": "confirmed"
            }
          ]
        },
        "category": [
          {
            "coding": [
              {
                "system": "http://terminology.hl7.org/CodeSystem/condition-category",
                "code": "problem-list-item",
                "display": "Problem List Item"
              }
            ]
          }
        ],
        "code": {
          "coding": [
            {
              "system": "http://snomed.info/sct",
              "code": "254878006",
              "display": "Uterine Adenosarcoma with Stromal Overgrowth"
            }
          ],
          "text": "Uterine Adenosarcoma with Stromal Overgrowth (T1bN0M0)"
        },
        "subject": {
          "reference": "Patient/patient-1"
        }
      }
    },
    {
      "resource": {
        "resourceType": "Condition",
        "id": "condition-2",
        "clinicalStatus": {
          "coding": [
            {
              "system": "http://terminology.hl7.org/CodeSystem/condition-clinical",
              "code": "active"
            }
          ]
        },
        "verificationStatus": {
          "coding": [
            {
              "system": "http://terminology.hl7.org/CodeSystem/condition-ver-status",
              "code": "confirmed"
            }
          ]
        },
        "category": [
          {
            "coding": [
              {
                "system": "http://terminology.hl7.org/CodeSystem/condition-category",
                "code": "problem-list-item",
                "display": "Problem List Item"
              }
            ]
          }
        ],
        "code": {
          "coding": [
            {
              "system": "http://snomed.info/sct",
              "code": "254878006",
              "display": "Adult Granulosa Cell Tumor (GCT) of the Right Ovary"
            }
          ],
          "text": "Adult Granulosa Cell Tumor (GCT) of the Right Ovary"
        },
        "subject": {
          "reference": "Patient/patient-1"
        }
      }
    },
    {
      "resource": {
        "resourceType": "Condition",
        "id": "condition-3",
        "clinicalStatus": {
          "coding": [
            {
              "system": "http://terminology.hl7.org/CodeSystem/condition-clinical",
              "code": "active"
            }
          ]
        },
        "verificationStatus": {
          "coding": [
            {
              "system": "http://terminology.hl7.org/CodeSystem/condition-ver-status",
              "code": "confirmed"
            }
          ]
        },
        "category": [
          {
            "coding": [
              {
                "system": "http://terminology.hl7.org/CodeSystem/condition-category",
                "code": "problem-list-item",
                "display": "Problem List Item"
              }
            ]
          }
        ],
        "code": {
          "coding": [
            {
              "system": "http://snomed.info/sct",
              "code": "254878006",
              "display": "Left Upper Lung Metastasis"
            }
          ],
          "text": "Left Upper Lung Metastasis"
        },
        "subject": {
          "reference": "Patient/patient-1"
        }
      }
    },
    {
      "resource": {
        "resourceType": "Procedure",
        "id": "procedure-1",
        "status": "completed",
        "code": {
          "coding": [
            {
              "system": "http://snomed.info/sct",
              "code": "274025005",
              "display": "Abdominal Modified Radical Hysterectomy with Bilateral Adnexectomy"
            }
          ],
          "text": "Abdominal Modified Radical Hysterectomy with Bilateral Adnexectomy"
        },
        "subject": {
          "reference": "Patient/patient-1"
        },
        "performedPeriod": {
          "start": "[REDACTED]",
          "end": "[REDACTED]"
        }
      }
    },
    {
      "resource": {
        "resourceType": "Procedure",
        "id": "procedure-2",
        "status": "completed",
        "code": {
          "coding": [
            {
              "system": "http://snomed.info/sct",
              "code": "274025006",
              "display": "Pelvic and Para-aortic Lymphadenectomy"
            }
          ],
          "text": "Pelvic and Para-aortic Lymphadenectomy"
        },
        "subject": {
          "reference": "Patient/patient-1"
        },
        "performedPeriod": {
          "start": "[REDACTED]",
          "end": "[REDACTED]"
        }
      }
    },
    {
      "resource": {
        "resourceType": "Procedure",
        "id": "procedure-3",
        "status": "completed",
        "code": {
          "coding": [
            {
              "system": "http://snomed.info/sct",
              "code": "274025007",
              "display": "Omentectomy"
            }
          ],
          "text": "Omentectomy"
        },
        "subject": {
          "reference": "Patient/patient-1"
        },
        "performedPeriod": {
          "start": "[REDACTED]",
          "end": "[REDACTED]"
        }
      }
    },
    {
      "resource": {
        "resourceType": "Procedure",
        "id": "procedure-4",
        "status": "completed",
        "code": {
          "coding": [
            {
              "system": "http://snomed.info/sct",
              "code": "274025008",
              "display": "Thoracoscopic Segmentectomy of Left Upper Lobe"
            }
          ],
          "text": "Thoracoscopic Segmentectomy of Left Upper Lobe"
        },
        "subject": {
          "reference": "Patient/patient-1"
        },
        "performedPeriod": {
          "start": "[REDACTED]",
          "end": "[REDACTED]"
        }
      }
    },
    {
      "resource": {
        "resourceType": "Observation",
        "id": "observation-1",
        "status": "final",
        "code": {
          "coding": [
            {
              "system": "http://loinc.org",
              "code": "75323-3",
              "display": "Condition at discharge"
            }
          ],
          "text": "Condition at Discharge"
        },
        "subject": {
          "reference": "Patient/patient-1"
        },
        "valueString": "clinically stable"
      }
    },
    {
      "resource": {
        "resourceType": "CarePlan",
        "id": "careplan-1",
        "status": "active",
        "intent": "plan",
        "title": "Follow-up care",
        "description": "Appropriate follow-up care and monitoring advised.",
        "subject": {
          "reference": "Patient/patient-1"
        }
      }
    }
  ]
}