{
  "resourceType": "Bundle",
  "type": "document",
  "entry": [
    {
      "resource": {
        "resourceType": "Patient",
        "id": "patient-1",
        "identifier": [
          {
            "system": "http://hospital.smarthealthit.org",
            "value": "patient-1"
          }
        ],
        "name": [
          {
            "use": "official",
            "family": "Patient",
            "given": [
              "1"
            ]
          }
        ],
        "gender": "male",
        "birthDate": "2012",
        "extension": [
          {
            "url": "http://hl7.org/fhir/StructureDefinition/patient-birthDate",
            "valueDateTime": "2012"
          }
        ]
      }
    },
    {
      "resource": {
        "resourceType": "Condition",
        "id": "condition-1",
        "subject": {
          "reference": "Patient/patient-1"
        },
        "code": {
          "coding": [
            {
              "system": "http://snomed.info/sct",
              "code": "312824007",
              "display": "Osteoporosis"
            }
          ],
          "text": "Osteoporosis"
        }
      }
    },
    {
      "resource": {
        "resourceType": "Condition",
        "id": "condition-2",
        "subject": {
          "reference": "Patient/patient-1"
        },
        "code": {
          "coding": [
            {
              "system": "http://snomed.info/sct",
              "code": "195967001",
              "display": "Asthma"
            }
          ],
          "text": "Asthma"
        }
      }
    },
    {
      "resource": {
        "resourceType": "Condition",
        "id": "condition-3",
        "subject": {
          "reference": "Patient/patient-1"
        },
        "code": {
          "coding": [
            {
              "system": "http://snomed.info/sct",
              "code": "84757009",
              "display": "Epilepsy"
            }
          ],
          "text": "Epilepsy"
        }
      }
    },
    {
      "resource": {
        "resourceType": "Condition",
        "id": "condition-4",
        "subject": {
          "reference": "Patient/patient-1"
        },
        "code": {
          "coding": [
            {
              "system": "http://snomed.info/sct",
              "code": "303689007",
              "display": "Neutropenia"
            }
          ],
          "text": "Neutropenia"
        }
      }
    },
    {
      "resource": {
        "resourceType": "Condition",
        "id": "condition-5",
        "subject": {
          "reference": "Patient/patient-1"
        },
        "code": {
          "coding": [
            {
              "system": "http://snomed.info/sct",
              "code": "408856003",
              "display": "Autism spectrum disorder"
            }
          ],
          "text": "Autism spectrum disorder"
        }
      }
    },
    {
      "resource": {
        "resourceType": "Procedure",
        "id": "procedure-1",
        "subject": {
          "reference": "Patient/patient-1"
        },
        "code": {
          "coding": [
            {
              "system": "http://snomed.info/sct",
              "code": "108241001",
              "display": "Bone biopsy"
            }
          ],
          "text": "Bone biopsy"
        },
        "outcome": {
          "coding": [
            {
              "system": "http://snomed.info/sct",
              "code": "312823001",
              "display": "Osteopenia"
            }
          ],
          "text": "Osteopenia"
        }
      }
    },
    {
      "resource": {
        "resourceType": "Procedure",
        "id": "procedure-2",
        "subject": {
          "reference": "Patient/patient-1"
        },
        "code": {
          "coding": [
            {
              "system": "http://snomed.info/sct",
              "code": "17404006",
              "display": "Surgery for undescended testes"
            }
          ],
          "text": "Surgery for undescended testes"
        }
      }
    },
    {
      "resource": {
        "resourceType": "Procedure",
        "id": "procedure-3",
        "subject": {
          "reference": "Patient/patient-1"
        },
        "code": {
          "coding": [
            {
              "system": "http://snomed.info/sct",
              "code": "6518009",
              "display": "Surgery for left-sided calcaneus talipes equinovarus"
            }
          ],
          "text": "Surgery for left-sided calcaneus talipes equinovarus"
        }
      }
    },
    {
      "resource": {
        "resourceType": "Procedure",
        "id": "procedure-4",
        "subject": {
          "reference": "Patient/patient-1"
        },
        "code": {
          "coding": [
            {
              "system": "http://snomed.info/sct",
              "code": "274025005",
              "display": "Surgery for right-sided developmental dysplasia of the hip"
            }
          ],
          "text": "Surgery for right-sided developmental dysplasia of the hip"
        }
      }
    },
    {
      "resource": {
        "resourceType": "MedicationStatement",
        "id": "medication-1",
        "subject": {
          "reference": "Patient/patient-1"
        },
        "medicationCodeableConcept": {
          "coding": [
            {
              "system": "http://www.nlm.nih.gov/research/umls/rxnorm",
              "code": "7052",
              "display": "Pamidronate"
            }
          ],
          "text": "Pamidronate"
        },
        "dosage": [
          {
            "timing": {
              "repeat": {
                "frequency": 1,
                "period": 3,
                "periodUnit": "mo"
              }
            }
          }
        ]
      }
    },
    {
      "resource": {
        "resourceType": "MedicationStatement",
        "id": "medication-2",
        "subject": {
          "reference": "Patient/patient-1"
        },
        "medicationCodeableConcept": {
          "coding": [
            {
              "system": "http://www.nlm.nih.gov/research/umls/rxnorm",
              "code": "6809",
              "display": "Melatonin"
            }
          ],
          "text": "Melatonin"
        }
      }
    },
    {
      "resource": {
        "resourceType": "MedicationStatement",
        "id": "medication-3",
        "subject": {
          "reference": "Patient/patient-1"
        },
        "medicationCodeableConcept": {
          "coding": [
            {
              "system": "http://www.nlm.nih.gov/research/umls/rxnorm",
              "code": "7052",
              "display": "Midazolam"
            }
          ],
          "text": "Midazolam"
        }
      }
    },
    {
      "resource": {
        "resourceType": "Observation",
        "id": "observation-1",
        "subject": {
          "reference": "Patient/patient-1"
        },
        "code": {
          "coding": [
            {
              "system": "http://loinc.org",
              "code": "38262-2",
              "display": "DXA Bone density"
            }
          ],
          "text": "DXA scan"
        },
        "valueString": "Reduced BMD with Z-scores of -3.4 at the lumbar vertebrae and a total body score of -2.5 adjusted for age and gender"
      }
    },
    {
      "resource": {
        "resourceType": "DiagnosticReport",
        "id": "diagnostic-report-1",
        "subject": {
          "reference": "Patient/patient-1"
        },
        "code": {
          "coding": [
            {
              "system": "http://loinc.org",
              "code": "81247-9",
              "display": "Trio whole-exome sequencing"
            }
          ],
          "text": "Trio whole-exome sequencing"
        },
        "conclusion": "De novo missense variant in NRXN1, interacts with COL1A1, associated with neurodevelopmental disorders/autism"
      }
    },
    {
      "resource": {
        "resourceType": "Encounter",
        "id": "encounter-1",
        "subject": {
          "reference": "Patient/patient-1"
        },
        "status": "finished",
        "class": {
          "system": "http://terminology.hl7.org/CodeSystem/v3-ActCode",
          "code": "IMP",
          "display": "inpatient"
        },
        "reasonCode": [
          {
            "coding": [
              {
                "system": "http://snomed.info/sct",
                "code": "312824007",
                "display": "Osteoporosis"
              }
            ],
            "text": "Management of osteoporosis, asthma, epilepsy, and neutropenia"
          }
        ],
        "diagnosis": [
          {
            "condition": {
              "reference": "Condition/condition-1"
            },
            "rank": 1
          }
        ],
        "period": {
          "start": "2022-03-20",
          "end": "2022-03-25"
        }
      }
    },
    {
      "resource": {
        "resourceType": "CarePlan",
        "id": "careplan-1",
        "intent": "plan",
        "status": "active",
        "subject": {
          "reference": "Patient/patient-1"
        },
        "activity": [
          {
            "detail": {
              "code": {
                "coding": [
                  {
                    "system": "http://snomed.info/sct",
                    "code": "312824007",
                    "display": "Osteoporosis"
                  }
                ],
                "text": "Treatment for osteoporosis with 3-monthly pamidronate infusions"
              },
              "status": "completed"
            }
          },
          {
            "detail": {
              "code": {
                "coding": [
                  {
                    "system": "http://snomed.info/sct",
                    "code": "195967001",
                    "display": "Asthma"
                  }
                ],
                "text": "Asthma management"
              },
              "status": "completed"
            }
          },
          {
            "detail": {
              "code": {
                "coding": [
                  {
                    "system": "http://snomed.info/sct",
                    "code": "84757009",
                    "display": "Epilepsy"
                  }
                ],
                "text": "Epilepsy management, midazolam for prolonged seizure"
              },
              "status": "completed"
            }
          },
          {
            "detail": {
              "code": {
                "coding": [
                  {
                    "system": "http://snomed.info/sct",
                    "code": "303689007",
                    "display": "Neutropenia"
                  }
                ],
                "text": "Neutropenia management"
              },
              "status": "completed"
            }
          },
          {
            "detail": {
              "code": {
                "coding": [
                  {
                    "system": "http://snomed.info/sct",
                    "code": "408856003",
                    "display": "Autism spectrum disorder"
                  }
                ],
                "text": "Continue with melatonin"
              },
              "status": "completed"
            }
          }
        ]
      }
    },
    {
      "resource": {
        "resourceType": "MedicationRequest",
        "id": "medicationrequest-1",
        "subject": {
          "reference": "Patient/patient-1"
        },
        "medicationCodeableConcept": {
          "coding": [
            {
              "system": "http://www.nlm.nih.gov/research/umls/rxnorm",
              "code": "6809",
              "display": "Melatonin"
            }
          ],
          "text": "Melatonin"
        },
        "status": "active",
        "intent": "order"
      }
    },
    {
      "resource": {
        "resourceType": "Appointment",
        "id": "appointment-1",
        "status": "booked",
        "description": "Follow-up appointment with a specialist for further monitoring",
        "participant": [
          {
            "actor": {
              "reference": "Patient/patient-1"
            },
            "status": "accepted"
          }
        ]
      }
    }
  ]
}