{
  "resourceType": "Bundle",
  "type": "document",
  "entry": [
    {
      "resource": {
        "resourceType": "Patient",
        "id": "patient-1",
        "gender": "male"
      }
    },
    {
      "resource": {
        "resourceType": "Condition",
        "id": "condition-1",
        "clinicalStatus": {
          "coding": [
            {
              "system": "http://terminology.hl7.org/CodeSystem/condition-clinical",
              "code": "active"
            }
          ]
        },
        "verificationStatus": {
          "coding": [
            {
              "system": "http://terminology.hl7.org/CodeSystem/condition-ver-status",
              "code": "confirmed"
            }
          ]
        },
        "category": [
          {
            "coding": [
              {
                "system": "http://terminology.hl7.org/CodeSystem/condition-category",
                "code": "encounter-diagnosis"
              }
            ]
          }
        ],
        "code": {
          "coding": [
            {
              "system": "http://snomed.info/sct",
              "code": "40930008",
              "display": "Hypothyroidism"
            }
          ]
        },
        "subject": {
          "reference": "Patient/patient-1"
        }
      }
    },
    {
      "resource": {
        "resourceType": "Observation",
        "id": "observation-1",
        "status": "final",
        "category": [
          {
            "coding": [
              {
                "system": "http://terminology.hl7.org/CodeSystem/observation-category",
                "code": "laboratory"
              }
            ]
          }
        ],
        "code": {
          "coding": [
            {
              "system": "http://loinc.org",
              "code": "3024-7",
              "display": "Serum creatine kinase"
            }
          ]
        },
        "valueQuantity": {
          "value": "elevated",
          "unit": "U/L"
        },
        "subject": {
          "reference": "Patient/patient-1"
        }
      }
    },
    {
      "resource": {
        "resourceType": "Observation",
        "id": "observation-2",
        "status": "final",
        "category": [
          {
            "coding": [
              {
                "system": "http://terminology.hl7.org/CodeSystem/observation-category",
                "code": "laboratory"
              }
            ]
          }
        ],
        "code": {
          "coding": [
            {
              "system": "http://loinc.org",
              "code": "14937-7",
              "display": "Myoglobin"
            }
          ]
        },
        "valueQuantity": {
          "value": "elevated",
          "unit": "ng/mL"
        },
        "subject": {
          "reference": "Patient/patient-1"
        }
      }
    },
    {
      "resource": {
        "resourceType": "Observation",
        "id": "observation-3",
        "status": "final",
        "category": [
          {
            "coding": [
              {
                "system": "http://terminology.hl7.org/CodeSystem/observation-category",
                "code": "laboratory"
              }
            ]
          }
        ],
        "code": {
          "coding": [
            {
              "system": "http://loinc.org",
              "code": "3016-3",
              "display": "Anti-thyroid peroxidase antibody"
            }
          ]
        },
        "valueString": "elevated",
        "subject": {
          "reference": "Patient/patient-1"
        }
      }
    },
    {
      "resource": {
        "resourceType": "Observation",
        "id": "observation-4",
        "status": "final",
        "category": [
          {
            "coding": [
              {
                "system": "http://terminology.hl7.org/CodeSystem/observation-category",
                "code": "laboratory"
              }
            ]
          }
        ],
        "code": {
          "coding": [
            {
              "system": "http://loinc.org",
              "code": "3020-5",
              "display": "Anti-thyroglobulin antibody"
            }
          ]
        },
        "valueString": "elevated",
        "subject": {
          "reference": "Patient/patient-1"
        }
      }
    },
    {
      "resource": {
        "resourceType": "Observation",
        "id": "observation-5",
        "status": "final",
        "category": [
          {
            "coding": [
              {
                "system": "http://terminology.hl7.org/CodeSystem/observation-category",
                "code": "imaging"
              }
            ]
          }
        ],
        "code": {
          "coding": [
            {
              "system": "http://snomed.info/sct",
              "code": "241611002",
              "display": "Transthoracic echocardiography"
            }
          ]
        },
        "valueCodeableConcept": {
          "coding": [
            {
              "system": "http://snomed.info/sct",
              "code": "252161000000108",
              "display": "Minimal pericardial effusion"
            }
          ]
        },
        "subject": {
          "reference": "Patient/patient-1"
        }
      }
    },
    {
      "resource": {
        "resourceType": "Procedure",
        "id": "procedure-1",
        "status": "completed",
        "code": {
          "coding": [
            {
              "system": "http://snomed.info/sct",
              "code": "432100008",
              "display": "Flexible laryngoscopy"
            }
          ]
        },
        "subject": {
          "reference": "Patient/patient-1"
        }
      }
    },
    {
      "resource": {
        "resourceType": "MedicationRequest",
        "id": "medicationrequest-1",
        "status": "active",
        "intent": "order",
        "medicationCodeableConcept": {
          "coding": [
            {
              "system": "http://www.nlm.nih.gov/research/umls/rxnorm",
              "code": "5640",
              "display": "Levothyroxine Sodium"
            }
          ]
        },
        "subject": {
          "reference": "Patient/patient-1"
        },
        "dosageInstruction": [
          {
            "text": "Take orally as prescribed"
          }
        ]
      }
    },
    {
      "resource": {
        "resourceType": "Encounter",
        "id": "encounter-1",
        "status": "finished",
        "class": {
          "system": "http://terminology.hl7.org/CodeSystem/v3-ActCode",
          "code": "IMP",
          "display": "inpatient encounter"
        },
        "subject": {
          "reference": "Patient/patient-1"
        },
        "period": {
          "start": "2023-10-01T00:00:00Z",
          "end": "2023-10-04T00:00:00Z"
        },
        "reasonCode": [
          {
            "coding": [
              {
                "system": "http://snomed.info/sct",
                "code": "40930008",
                "display": "Hypothyroidism"
              }
            ]
          }
        ],
        "diagnosis": [
          {
            "condition": {
              "reference": "Condition/condition-1"
            }
          }
        ]
      }
    },
    {
      "resource": {
        "resourceType": "CarePlan",
        "id": "careplan-1",
        "status": "active",
        "intent": "plan",
        "title": "Discharge Plan",
        "description": "The patient was instructed to follow up with his primary care physician and endocrinologist for further management of his thyroid condition.",
        "subject": {
          "reference": "Patient/patient-1"
        }
      }
    }
  ]
}