{
  "resourceType": "Bundle",
  "type": "document",
  "entry": [
    {
      "resource": {
        "resourceType": "Patient",
        "gender": "male",
        "age": 62
      }
    },
    {
      "resource": {
        "resourceType": "Encounter",
        "status": "finished",
        "type": [
          {
            "coding": [
              {
                "system": "http://snomed.info/sct",
                "code": "32485007",
                "display": "Hospital admission"
              }
            ]
          }
        ],
        "period": {
          "start": "N/A",
          "end": "N/A"
        },
        "reasonCode": [
          {
            "text": "Elective left and right heart catheterization as a pre-transplant evaluation"
          }
        ]
      }
    },
    {
      "resource": {
        "resourceType": "Condition",
        "clinicalStatus": {
          "coding": [
            {
              "system": "http://terminology.hl7.org/CodeSystem/condition-clinical",
              "code": "active"
            }
          ]
        },
        "verificationStatus": {
          "coding": [
            {
              "system": "http://terminology.hl7.org/CodeSystem/condition-ver-status",
              "code": "confirmed"
            }
          ]
        },
        "code": {
          "coding": [
            {
              "system": "http://snomed.info/sct",
              "code": "439127006",
              "display": "Thrombosis of inferior vena cava"
            }
          ],
          "text": "Occlusive thrombus of the IVC from the renal veins to the level of the cavoatrial junction"
        },
        "bodySite": [
          {
            "coding": [
              {
                "system": "http://snomed.info/sct",
                "code": "81923005",
                "display": "Inferior vena cava"
              }
            ]
          }
        ]
      }
    },
    {
      "resource": {
        "resourceType": "Condition",
        "clinicalStatus": {
          "coding": [
            {
              "system": "http://terminology.hl7.org/CodeSystem/condition-clinical",
              "code": "active"
            }
          ]
        },
        "verificationStatus": {
          "coding": [
            {
              "system": "http://terminology.hl7.org/CodeSystem/condition-ver-status",
              "code": "confirmed"
            }
          ]
        },
        "code": {
          "coding": [
            {
              "system": "http://snomed.info/sct",
              "code": "128545000",
              "display": "Thrombosis of portal vein"
            }
          ],
          "text": "Thrombus in the portal vein"
        }
      }
    },
    {
      "resource": {
        "resourceType": "Condition",
        "clinicalStatus": {
          "coding": [
            {
              "system": "http://terminology.hl7.org/CodeSystem/condition-clinical",
              "code": "active"
            }
          ]
        },
        "verificationStatus": {
          "coding": [
            {
              "system": "http://terminology.hl7.org/CodeSystem/condition-ver-status",
              "code": "confirmed"
            }
          ]
        },
        "code": {
          "coding": [
            {
              "system": "http://snomed.info/sct",
              "code": "239873007",
              "display": "Esophageal varices"
            }
          ],
          "text": "Large esophageal varices"
        }
      }
    },
    {
      "resource": {
        "resourceType": "Procedure",
        "status": "completed",
        "code": {
          "coding": [
            {
              "system": "http://snomed.info/sct",
              "code": "180325003",
              "display": "Palliative procedure"
            }
          ],
          "text": "Palliative stenting of the IVC"
        },
        "reasonCode": [
          {
            "text": "Relieve pain and improve quality of life"
          }
        ],
        "bodySite": [
          {
            "coding": [
              {
                "system": "http://snomed.info/sct",
                "code": "81923005",
                "display": "Inferior vena cava"
              }
            ]
          }
        ]
      }
    },
    {
      "resource": {
        "resourceType": "Procedure",
        "status": "completed",
        "code": {
          "coding": [
            {
              "system": "http://snomed.info/sct",
              "code": "427028005",
              "display": "Right heart catheterization"
            }
          ],
          "text": "Right internal jugular (IJ) and right femoral vein accesses obtained"
        },
        "bodySite": [
          {
            "coding": [
              {
                "system": "http://snomed.info/sct",
                "code": "181867003",
                "display": "Internal jugular vein structure"
              }
            ]
          },
          {
            "coding": [
              {
                "system": "http://snomed.info/sct",
                "code": "181872004",
                "display": "Femoral vein structure"
              }
            ]
          }
        ]
      }
    },
    {
      "resource": {
        "resourceType": "Procedure",
        "status": "completed",
        "code": {
          "coding": [
            {
              "system": "http://snomed.info/sct",
              "code": "180325003",
              "display": "Palliative procedure"
            }
          ],
          "text": "IVC ballooning and stenting"
        },
        "bodySite": [
          {
            "coding": [
              {
                "system": "http://snomed.info/sct",
                "code": "81923005",
                "display": "Inferior vena cava"
              }
            ]
          }
        ],
        "usedReference": [
          {
            "reference": "Device/GlidewireAdvantage"
          },
          {
            "reference": "Device/7FrenchSwanGanzCatheter"
          },
          {
            "reference": "Device/MultipurposeCatheter"
          },
          {
            "reference": "Device/9x80MustangBalloon"
          },
          {
            "reference": "Device/22x70mmWallstent"
          },
          {
            "reference": "Device/18x60BostonScientificEsophagealBalloon"
          },
          {
            "reference": "Device/7FrSnare"
          }
        ]
      }
    },
    {
      "resource": {
        "resourceType": "Device",
        "id": "GlidewireAdvantage",
        "deviceName": [
          {
            "name": "Glidewire Advantage",
            "type": "model"
          }
        ]
      }
    },
    {
      "resource": {
        "resourceType": "Device",
        "id": "7FrenchSwanGanzCatheter",
        "deviceName": [
          {
            "name": "7-French Swan-Ganz catheter",
            "type": "model"
          }
        ]
      }
    },
    {
      "resource": {
        "resourceType": "Device",
        "id": "MultipurposeCatheter",
        "deviceName": [
          {
            "name": "Multipurpose catheter",
            "type": "model"
          }
        ]
      }
    },
    {
      "resource": {
        "resourceType": "Device",
        "id": "9x80MustangBalloon",
        "deviceName": [
          {
            "name": "9 × 80 Mustang balloon",
            "type": "model"
          }
        ]
      }
    },
    {
      "resource": {
        "resourceType": "Device",
        "id": "22x70mmWallstent",
        "deviceName": [
          {
            "name": "22 × 70 mm Wallstent",
            "type": "model"
          }
        ]
      }
    },
    {
      "resource": {
        "resourceType": "Device",
        "id": "18x60BostonScientificEsophagealBalloon",
        "deviceName": [
          {
            "name": "18 × 60 Boston Scientific esophageal balloon",
            "type": "model"
          }
        ]
      }
    },
    {
      "resource": {
        "resourceType": "Device",
        "id": "7FrSnare",
        "deviceName": [
          {
            "name": "7-Fr snare",
            "type": "model"
          }
        ]
      }
    }
  ]
}