{
  "resourceType": "Bundle",
  "type": "document",
  "entry": [
    {
      "resource": {
        "resourceType": "Patient",
        "id": "Case5",
        "name": [
          {
            "text": "Case 5"
          }
        ],
        "gender": "female",
        "birthDate": "1987-01-01"
      }
    },
    {
      "resource": {
        "resourceType": "Encounter",
        "id": "encounter1",
        "status": "finished",
        "class": {
          "system": "http://terminology.hl7.org/CodeSystem/v3-ActCode",
          "code": "IMP",
          "display": "inpatient encounter"
        },
        "subject": {
          "reference": "Patient/Case5"
        },
        "period": {
          "start": "[Date]",
          "end": "[Date]"
        },
        "reasonCode": [
          {
            "text": "Bacterial meningitis infection"
          }
        ]
      }
    },
    {
      "resource": {
        "resourceType": "Condition",
        "id": "condition1",
        "clinicalStatus": {
          "coding": [
            {
              "system": "http://terminology.hl7.org/CodeSystem/condition-clinical",
              "code": "active"
            }
          ]
        },
        "verificationStatus": {
          "coding": [
            {
              "system": "http://terminology.hl7.org/CodeSystem/condition-ver-status",
              "code": "confirmed"
            }
          ]
        },
        "category": [
          {
            "coding": [
              {
                "system": "http://terminology.hl7.org/CodeSystem/condition-category",
                "code": "encounter-diagnosis",
                "display": "Encounter Diagnosis"
              }
            ]
          }
        ],
        "code": {
          "coding": [
            {
              "system": "http://snomed.info/sct",
              "code": "7180009",
              "display": "Bacterial meningitis"
            }
          ],
          "text": "Bacterial meningitis infection caused by Neisseria meningitidis (Serotype C)"
        },
        "subject": {
          "reference": "Patient/Case5"
        }
      }
    },
    {
      "resource": {
        "resourceType": "Condition",
        "id": "condition2",
        "clinicalStatus": {
          "coding": [
            {
              "system": "http://terminology.hl7.org/CodeSystem/condition-clinical",
              "code": "active"
            }
          ]
        },
        "verificationStatus": {
          "coding": [
            {
              "system": "http://terminology.hl7.org/CodeSystem/condition-ver-status",
              "code": "confirmed"
            }
          ]
        },
        "category": [
          {
            "coding": [
              {
                "system": "http://terminology.hl7.org/CodeSystem/condition-category",
                "code": "encounter-diagnosis",
                "display": "Encounter Diagnosis"
              }
            ]
          }
        ],
        "code": {
          "coding": [
            {
              "system": "http://snomed.info/sct",
              "code": "302215000",
              "display": "Thrombocytopenia"
            }
          ],
          "text": "Thrombocytopenia"
        },
        "subject": {
          "reference": "Patient/Case5"
        }
      }
    },
    {
      "resource": {
        "resourceType": "Condition",
        "id": "condition3",
        "clinicalStatus": {
          "coding": [
            {
              "system": "http://terminology.hl7.org/CodeSystem/condition-clinical",
              "code": "active"
            }
          ]
        },
        "verificationStatus": {
          "coding": [
            {
              "system": "http://terminology.hl7.org/CodeSystem/condition-ver-status",
              "code": "confirmed"
            }
          ]
        },
        "category": [
          {
            "coding": [
              {
                "system": "http://terminology.hl7.org/CodeSystem/condition-category",
                "code": "encounter-diagnosis",
                "display": "Encounter Diagnosis"
              }
            ]
          }
        ],
        "code": {
          "coding": [
            {
              "system": "http://snomed.info/sct",
              "code": "43116000",
              "display": "Acute renal failure syndrome"
            }
          ],
          "text": "Acute renal failure"
        },
        "subject": {
          "reference": "Patient/Case5"
        }
      }
    },
    {
      "resource": {
        "resourceType": "Condition",
        "id": "condition4",
        "clinicalStatus": {
          "coding": [
            {
              "system": "http://terminology.hl7.org/CodeSystem/condition-clinical",
              "code": "active"
            }
          ]
        },
        "verificationStatus": {
          "coding": [
            {
              "system": "http://terminology.hl7.org/CodeSystem/condition-ver-status",
              "code": "confirmed"
            }
          ]
        },
        "category": [
          {
            "coding": [
              {
                "system": "http://terminology.hl7.org/CodeSystem/condition-category",
                "code": "encounter-diagnosis",
                "display": "Encounter Diagnosis"
              }
            ]
          }
        ],
        "code": {
          "coding": [
            {
              "system": "http://snomed.info/sct",
              "code": "133873004",
              "display": "Inflammation of meninges"
            }
          ],
          "text": "Inflammation"
        },
        "subject": {
          "reference": "Patient/Case5"
        }
      }
    },
    {
      "resource": {
        "resourceType": "Procedure",
        "id": "procedure1",
        "status": "completed",
        "code": {
          "coding": [
            {
              "system": "http://snomed.info/sct",
              "code": "763158003",
              "display": "Continuous veno-venous hemodiafiltration"
            }
          ],
          "text": "CVVHDF (Prismaflex, Oxiris, Baxter, USA)"
        },
        "subject": {
          "reference": "Patient/Case5"
        },
        "performedPeriod": {
          "start": "[Date]",
          "end": "[Date]"
        }
      }
    },
    {
      "resource": {
        "resourceType": "Procedure",
        "id": "procedure2",
        "status": "completed",
        "code": {
          "coding": [
            {
              "system": "http://snomed.info/sct",
              "code": "763158003",
              "display": "Hemoadsorption therapy"
            }
          ],
          "text": "Cytosorb"
        },
        "subject": {
          "reference": "Patient/Case5"
        },
        "performedPeriod": {
          "start": "[Date]",
          "end": "[Date]"
        }
      }
    },
    {
      "resource": {
        "resourceType": "MedicationAdministration",
        "id": "medication1",
        "status": "completed",
        "medicationCodeableConcept": {
          "coding": [
            {
              "system": "http://www.nlm.nih.gov/research/umls/rxnorm",
              "code": "72761",
              "display": "Norepinephrine"
            }
          ],
          "text": "Norepinephrine"
        },
        "subject": {
          "reference": "Patient/Case5"
        },
        "effectivePeriod": {
          "start": "[Date]",
          "end": "[Date]"
        }
      }
    },
    {
      "resource": {
        "resourceType": "MedicationAdministration",
        "id": "medication2",
        "status": "completed",
        "medicationCodeableConcept": {
          "coding": [
            {
              "system": "http://www.nlm.nih.gov/research/umls/rxnorm",
              "code": "3413",
              "display": "Dobutamine"
            }
          ],
          "text": "Dobutamine"
        },
        "subject": {
          "reference": "Patient/Case5"
        },
        "effectivePeriod": {
          "start": "[Date]",
          "end": "[Date]"
        }
      }
    },
    {
      "resource": {
        "resourceType": "Condition",
        "id": "condition5",
        "clinicalStatus": {
          "coding": [
            {
              "system": "http://terminology.hl7.org/CodeSystem/condition-clinical",
              "code": "active"
            }
          ]
        },
        "verificationStatus": {
          "coding": [
            {
              "system": "http://terminology.hl7.org/CodeSystem/condition-ver-status",
              "code": "confirmed"
            }
          ]
        },
        "code": {
          "coding": [
            {
              "system": "http://snomed.info/sct",
              "code": "233604007",
              "display": "Septic embolism"
            }
          ],
          "text": "Septic embolism complication"
        },
        "subject": {
          "reference": "Patient/Case5"
        }
      }
    },
    {
      "resource": {
        "resourceType": "Procedure",
        "id": "procedure3",
        "status": "unknown",
        "code": {
          "coding": [
            {
              "system": "http://snomed.info/sct",
              "code": "81723002",
              "display": "Amputation of toe"
            }
          ],
          "text": "Possible amputation of one toe"
        },
        "subject": {
          "reference": "Patient/Case5"
        }
      }
    },
    {
      "resource": {
        "resourceType": "DocumentReference",
        "id": "dischargeInstructions",
        "status": "current",
        "subject": {
          "reference": "Patient/Case5"
        },
        "content": [
          {
            "attachment": {
              "contentType": "text/plain",
              "data": "Mrs. [Name] is being discharged with instructions to monitor symptoms and follow up with necessary medical specialists. The patient should ensure strict adherence to follow-up appointments and recommended medical interventions for the successful management of her condition."
            }
          }
        ]
      }
    }
  ]
}